varsdump/__init__.py
varsdump/lib.py
varsdump-1.0.2.dist-info/LICENSE
varsdump-1.0.2.dist-info/METADATA
varsdump-1.0.2.dist-info/WHEEL
varsdump-1.0.2.dist-info/top_level.txt
varsdump-1.0.2.dist-info/RECORD
