Metadata-Version: 2.1
Name: varsdump
Version: 1.0.2
Summary: A simple library for easy handling of .env files and environment variables configurations
Home-page: https://github.com/frontdevops/vardump
Download-URL: https://github.com/frontdevops/vardump/archive/refs/tags/1.0.2.tar.gz
Author: Alexander Majorov
Author-email: Alexander Majorov <alexander.majorov@gmail.com>
License: MIT
Project-URL: Homepage, https://github.com/frontdevops/vardump
Project-URL: Documentation, https://github.com/frontdevops/vardump/blob/main/README.md
Project-URL: Bug Tracker, https://github.com/frontdevops/vardump/issues
Keywords: pypi,config,library,varsdump,var,dump,vardump,vardump
Classifier: Programming Language :: Python :: 3
Classifier: License :: OSI Approved :: MIT License
Classifier: Operating System :: OS Independent
Requires-Python: >=3.10.8
License-File: LICENSE
Requires-Dist: python-dotenv (>=0.21.0)
Provides-Extra: dev
Requires-Dist: pytest (>=3.7) ; extra == 'dev'
Requires-Dist: check-manifest ; extra == 'dev'
Requires-Dist: twine ; extra == 'dev'
